{
  "elements": [
    { "name": "html", "attributes": { "lang": "domain.language" }, "elements":  [
      { "name": "head", "attributes": {}, "elements":  [
        { "name": "meta", "attributes": { "charset": "UTF-8" }, "elements":  [], "innerHTML": "", "selfClosing": true },
        { "name": "title", "attributes": {}, "elements":  [], "innerHTML": "lexicon.td_tddh", "selfClosing": false },
        { "name": "meta", "attributes": { "name": "description", "content": "lexicon.tien_my_hieu,lexicon.tu_duc" }, "elements":  [], "innerHTML": "", "selfClosing": true },
        { "name": "meta", "attributes": { "name": "keywords", "content": "lexicon.tu_duc,lexicon.money,lexicon.vietnam" }, "elements":  [], "innerHTML": "", "selfClosing": true },
        { "name": "meta", "attributes": { "name": "viewport", "content": "width=device-width, initial-scale=1.0" }, "elements":  [], "innerHTML": "", "selfClosing": true },
        { "name": "link", "attributes": { "rel": "stylesheet", "href": "__CDN__css/tienmyhieu-domain.language.css" }, "elements":  [], "innerHTML": "", "selfClosing": true },
        { "name": "link", "attributes": { "rel": "icon", "href": "__IMAGES__favicon.png", "type": "image/png" }, "elements":  [], "innerHTML": "", "selfClosing": true }
      ], "innerHTML": "", "selfClosing": false },
      { "name": "body", "attributes": {}, "elements":  [
        { "name": "div", "attributes": { "class": "tmh_body" }, "elements":  [
          { "name": "div", "attributes": { "class": "tmh_top_bar" }, "elements":  [
            { "name": "div", "attributes": { "class": "tmh_navigation" }, "elements":  [
              { "name": "a", "attributes": { "class": "tmh_a", "href": "HTTP_HOST", "title": "lexicon.tien_my_hieu" }, "elements":  [], "innerHTML": "lexicon.tien_my_hieu", "selfClosing": false },
              { "name": "span", "attributes": { "class": "tmh_navigation_chevron" }, "elements":  [], "innerHTML": "&raquo;", "selfClosing": false },
              { "name": "a", "attributes": { "class": "tmh_a", "href": "routes.3n3shibu", "title": "lexicon.tu_duc" }, "elements":  [], "innerHTML": "lexicon.tu_duc", "selfClosing": false },
              { "name": "span", "attributes": { "class": "tmh_navigation_chevron" }, "elements":  [], "innerHTML": "&raquo;", "selfClosing": false },
              { "name": "span", "attributes": {}, "elements":  [], "innerHTML": "lexicon.tddh", "selfClosing": false }
            ], "innerHTML": "", "selfClosing": false }
          ], "innerHTML": "", "selfClosing": false },
          { "name": "div", "attributes": { "class": "tmh_title" }, "elements":  [], "innerHTML": "lexicon.tu_duc", "selfClosing": false },
          { "name": "div", "attributes": { "class": "tmh_elements" }, "elements":  [
            { "name": "div", "attributes": { "class": "tmh_element_title" }, "elements":  [], "innerHTML": "lexicon.tddh", "selfClosing": false },
            { "name": "div", "attributes": { "class": "tmh_inscriptions" }, "elements":  [
              { "name": "span", "attributes": {}, "elements":  [], "innerHTML": "lexicon.obverse", "selfClosing": false },
              { "name": "span", "attributes": { "class": "tmh_inscription" }, "elements":  [], "innerHTML": "inscriptions.8q1x00vs", "selfClosing": false },
              { "name": "span", "attributes": {}, "elements":  [], "innerHTML": "lexicon.reverse", "selfClosing": false },
              { "name": "span", "attributes": { "class": "tmh_inscription" }, "elements":  [], "innerHTML": "inscriptions.yliohiq2", "selfClosing": false }
            ], "innerHTML": "", "selfClosing": false },
            { "name": "div", "attributes": { "class": "tmh_specimen" }, "elements":  [
              { "name": "span", "attributes": { "class": "tmh_specimen_info", "name": "3" }, "elements":  [], "innerHTML": "lexicon.BTTPHCM_TD", "selfClosing": false }
            ], "innerHTML": "", "selfClosing": false },
            { "name": "div", "attributes": { "class": "tmh_image_route" }, "elements":  [
              { "name": "a", "attributes": { "class": "tmh_a_img", "href": "routes.bq3m5q9z", "title": "lexicon.td_tddh" }, "elements":  [
                { "name": "img", "attributes": { "alt": "lexicon.td_tddh", "class": "tmh_img", "src": "__IMAGES____PREVIEW_SIZE__/f6638cec01b5493182fbcdb4bd4b3e99-1.png" }, "elements":  [], "innerHTML": "", "selfClosing": true }
              ], "innerHTML": "", "selfClosing": false },
              { "name": "a", "attributes": { "class": "tmh_a_img", "href": "routes.bq3m5q9z", "title": "lexicon.td_tddh" }, "elements":  [
                { "name": "img", "attributes": { "alt": "lexicon.td_tddh", "class": "tmh_img", "src": "__IMAGES____PREVIEW_SIZE__/f6638cec01b5493182fbcdb4bd4b3e99-2.png" }, "elements":  [], "innerHTML": "", "selfClosing": true }
              ], "innerHTML": "", "selfClosing": false }
            ], "innerHTML": "", "selfClosing": false },
            { "name": "br", "attributes": {}, "elements":  [], "innerHTML": "", "selfClosing": true },
            { "name": "div", "attributes": { "class": "tmh_specimen" }, "elements":  [
              { "name": "span", "attributes": { "class": "tmh_specimen_info", "name": "1788" }, "elements":  [], "innerHTML": "lexicon.CMV_acronym", "selfClosing": false }
            ], "innerHTML": "", "selfClosing": false },
            { "name": "div", "attributes": { "class": "tmh_image_route" }, "elements":  [
              { "name": "a", "attributes": { "class": "tmh_a_img", "href": "routes.ntrt43rr", "title": "lexicon.td_tddh" }, "elements":  [
                { "name": "img", "attributes": { "alt": "lexicon.td_tddh", "class": "tmh_img", "src": "__IMAGES____PREVIEW_SIZE__/738bbe7fe4dc4e649df9d03974e80ca4-1.png" }, "elements":  [], "innerHTML": "", "selfClosing": true }
              ], "innerHTML": "", "selfClosing": false },
              { "name": "a", "attributes": { "class": "tmh_a_img", "href": "routes.ntrt43rr", "title": "lexicon.td_tddh" }, "elements":  [
                { "name": "img", "attributes": { "alt": "lexicon.td_tddh", "class": "tmh_img", "src": "__IMAGES____PREVIEW_SIZE__/738bbe7fe4dc4e649df9d03974e80ca4-2.png" }, "elements":  [], "innerHTML": "", "selfClosing": true }
              ], "innerHTML": "", "selfClosing": false }
            ], "innerHTML": "", "selfClosing": false },
            { "name": "br", "attributes": {}, "elements":  [], "innerHTML": "", "selfClosing": true },
            { "name": "div", "attributes": { "class": "tmh_specimen" }, "elements":  [
              { "name": "span", "attributes": { "class": "tmh_specimen_info", "name": "473" }, "elements":  [], "innerHTML": "lexicon.NA_acronym", "selfClosing": false }
            ], "innerHTML": "", "selfClosing": false },
            { "name": "div", "attributes": { "class": "tmh_image_route" }, "elements":  [
              { "name": "img", "attributes": { "alt": "", "class": "tmh_img", "src": "__IMAGES____PREVIEW_SIZE__/35609f0ec63d40c9b0cca4f29cc089d0.png" }, "elements":  [], "innerHTML": "", "selfClosing": true },
              { "name": "a", "attributes": { "class": "tmh_a_img", "href": "routes.2axjmwdq", "title": "lexicon.td_tddh" }, "elements":  [
                { "name": "img", "attributes": { "alt": "lexicon.td_tddh", "class": "tmh_img", "src": "__IMAGES____PREVIEW_SIZE__/2fec8b407b494c32a8c00704478456c0-2.png" }, "elements":  [], "innerHTML": "", "selfClosing": true }
              ], "innerHTML": "", "selfClosing": false }
            ], "innerHTML": "", "selfClosing": false },
            { "name": "br", "attributes": {}, "elements":  [], "innerHTML": "", "selfClosing": true },
            { "name": "div", "attributes": { "class": "tmh_element_title" }, "elements":  [], "innerHTML": "lexicon.references", "selfClosing": false },
            { "name": "div", "attributes": { "class": "tmh_references" }, "elements":  [
              { "name": "div", "attributes": { "class": "tmh_reference" }, "elements":  [
                { "name": "span", "attributes": {}, "elements":  [], "innerHTML": "lexicon.BTTPHCM_TD_full", "selfClosing": false }
              ], "innerHTML": "", "selfClosing": false },
              { "name": "div", "attributes": { "class": "tmh_reference" }, "elements":  [
                { "name": "span", "attributes": {}, "elements":  [], "innerHTML": "lexicon.ANMHDQYJ_full", "selfClosing": false },
                { "name": "span", "attributes": { "name": "120,198" }, "elements":  [], "innerHTML": "lexicon.page", "selfClosing": false }
              ], "innerHTML": "", "selfClosing": false },
              { "name": "div", "attributes": { "class": "tmh_reference" }, "elements":  [
                { "name": "span", "attributes": {}, "elements":  [], "innerHTML": "lexicon.ANMHDQTP_full", "selfClosing": false },
                { "name": "span", "attributes": { "name": "308" }, "elements":  [], "innerHTML": "lexicon.page", "selfClosing": false }
              ], "innerHTML": "", "selfClosing": false },
              { "name": "div", "attributes": { "class": "tmh_reference" }, "elements":  [
                { "name": "span", "attributes": {}, "elements":  [], "innerHTML": "lexicon.CMVC_full", "selfClosing": false },
                { "name": "span", "attributes": { "name": "381" }, "elements":  [], "innerHTML": "lexicon.page", "selfClosing": false }
              ], "innerHTML": "", "selfClosing": false },
              { "name": "div", "attributes": { "class": "tmh_reference" }, "elements":  [
                { "name": "span", "attributes": {}, "elements":  [], "innerHTML": "lexicon.TCVN2_full", "selfClosing": false },
                { "name": "span", "attributes": { "name": "131" }, "elements":  [], "innerHTML": "lexicon.page", "selfClosing": false }
              ], "innerHTML": "", "selfClosing": false },
              { "name": "div", "attributes": { "class": "tmh_reference" }, "elements":  [
                { "name": "span", "attributes": {}, "elements":  [], "innerHTML": "lexicon.TCVN_full", "selfClosing": false },
                { "name": "span", "attributes": { "name": "235" }, "elements":  [], "innerHTML": "lexicon.page", "selfClosing": false }
              ], "innerHTML": "", "selfClosing": false },
              { "name": "div", "attributes": { "class": "tmh_reference" }, "elements":  [
                { "name": "span", "attributes": {}, "elements":  [], "innerHTML": "lexicon.CMV_full", "selfClosing": false },
                { "name": "span", "attributes": { "name": "97," }, "elements":  [], "innerHTML": "lexicon.page", "selfClosing": false },
                { "name": "span", "attributes": { "name": "31," }, "elements":  [], "innerHTML": "lexicon.plate", "selfClosing": false }
              ], "innerHTML": "", "selfClosing": false },
              { "name": "div", "attributes": { "class": "tmh_reference" }, "elements":  [
                { "name": "span", "attributes": {}, "elements":  [], "innerHTML": "lexicon.TCTD_full", "selfClosing": false },
                { "name": "span", "attributes": { "name": "63" }, "elements":  [], "innerHTML": "lexicon.page", "selfClosing": false }
              ], "innerHTML": "", "selfClosing": false },
              { "name": "div", "attributes": { "class": "tmh_reference" }, "elements":  [
                { "name": "span", "attributes": {}, "elements":  [], "innerHTML": "lexicon.COTA_full", "selfClosing": false },
                { "name": "span", "attributes": { "name": "40" }, "elements":  [], "innerHTML": "lexicon.page", "selfClosing": false }
              ], "innerHTML": "", "selfClosing": false },
              { "name": "div", "attributes": { "class": "tmh_reference" }, "elements":  [
                { "name": "span", "attributes": {}, "elements":  [], "innerHTML": "lexicon.CAC_full", "selfClosing": false },
                { "name": "span", "attributes": { "name": "38" }, "elements":  [], "innerHTML": "lexicon.page", "selfClosing": false }
              ], "innerHTML": "", "selfClosing": false },
              { "name": "div", "attributes": { "class": "tmh_reference" }, "elements":  [
                { "name": "span", "attributes": {}, "elements":  [], "innerHTML": "lexicon.AEN_full", "selfClosing": false },
                { "name": "span", "attributes": { "name": "467" }, "elements":  [], "innerHTML": "lexicon.page", "selfClosing": false }
              ], "innerHTML": "", "selfClosing": false },
              { "name": "div", "attributes": { "class": "tmh_reference" }, "elements":  [
                { "name": "span", "attributes": {}, "elements":  [], "innerHTML": "lexicon.NA_full", "selfClosing": false },
                { "name": "span", "attributes": { "name": "191," }, "elements":  [], "innerHTML": "lexicon.page", "selfClosing": false },
                { "name": "span", "attributes": { "name": "35" }, "elements":  [], "innerHTML": "lexicon.plate", "selfClosing": false }
              ], "innerHTML": "", "selfClosing": false }
            ], "innerHTML": "", "selfClosing": false },
            { "name": "br", "attributes": {}, "elements":  [], "innerHTML": "", "selfClosing": true },
            { "name": "div", "attributes": { "class": "tmh_creative_commons" }, "elements":  [
              { "name": "span", "attributes": {}, "elements":  [], "innerHTML": "lexicon.cc_this_image", "selfClosing": false },
              { "name": "span", "attributes": {}, "elements":  [], "innerHTML": "lexicon.cc_licensed", "selfClosing": false },
              { "name": "br", "attributes": {}, "elements":  [], "innerHTML": "", "selfClosing": true },
              { "name": "div", "attributes": { "class": "tmh_image_route" }, "elements":  [
                { "name": "a", "attributes": { "class": "tmh_a_external", "href": "lexicon.cc_deed_url", "rel": "license", "target": "_blank", "title": "lexicon.cc_image_alt" }, "elements":  [], "innerHTML": "lexicon.cc_url_text", "selfClosing": false }
              ], "innerHTML": "", "selfClosing": false }
            ], "innerHTML": "", "selfClosing": false }
          ], "innerHTML": "", "selfClosing": false }
        ], "innerHTML": "", "selfClosing": false }
      ], "innerHTML": "", "selfClosing": false }
    ], "innerHTML": "", "selfClosing": false }
  ]
}