{
  "elements": [
    { "name": "html", "attributes": { "lang": "domain.language" }, "elements":  [
      { "name": "head", "attributes": {}, "elements":  [
        { "name": "meta", "attributes": { "charset": "UTF-8" }, "elements":  [], "innerHTML": "", "selfClosing": true },
        { "name": "title", "attributes": {}, "elements":  [], "innerHTML": "lexicon.mm_vdddtmdd", "selfClosing": false },
        { "name": "meta", "attributes": { "name": "description", "content": "lexicon.tien_my_hieu,lexicon.minh_menh" }, "elements":  [], "innerHTML": "", "selfClosing": true },
        { "name": "meta", "attributes": { "name": "keywords", "content": "lexicon.minh_menh,lexicon.money,lexicon.vietnam" }, "elements":  [], "innerHTML": "", "selfClosing": true },
        { "name": "meta", "attributes": { "name": "viewport", "content": "width=device-width, initial-scale=1.0" }, "elements":  [], "innerHTML": "", "selfClosing": true },
        { "name": "link", "attributes": { "rel": "stylesheet", "href": "__CDN__css/tienmyhieu-domain.language.css" }, "elements":  [], "innerHTML": "", "selfClosing": true },
        { "name": "link", "attributes": { "rel": "icon", "href": "__IMAGES__favicon.png", "type": "image/png" }, "elements":  [], "innerHTML": "", "selfClosing": true }
      ], "innerHTML": "", "selfClosing": false },
      { "name": "body", "attributes": {}, "elements":  [
        { "name": "div", "attributes": { "class": "tmh_body" }, "elements":  [
          { "name": "div", "attributes": { "class": "tmh_top_bar" }, "elements":  [
            { "name": "div", "attributes": { "class": "tmh_navigation" }, "elements":  [
              { "name": "a", "attributes": { "class": "tmh_a", "href": "HTTP_HOST", "title": "lexicon.tien_my_hieu" }, "elements":  [], "innerHTML": "lexicon.tien_my_hieu", "selfClosing": false },
              { "name": "span", "attributes": { "class": "tmh_navigation_chevron" }, "elements":  [], "innerHTML": "&raquo;", "selfClosing": false },
              { "name": "a", "attributes": { "class": "tmh_a", "href": "routes.1fwjkgi2", "title": "lexicon.minh_menh" }, "elements":  [], "innerHTML": "lexicon.minh_menh", "selfClosing": false },
              { "name": "span", "attributes": { "class": "tmh_navigation_chevron" }, "elements":  [], "innerHTML": "&raquo;", "selfClosing": false },
              { "name": "span", "attributes": {}, "elements":  [], "innerHTML": "lexicon.vdddtmdd", "selfClosing": false }
            ], "innerHTML": "", "selfClosing": false }
          ], "innerHTML": "", "selfClosing": false },
          { "name": "div", "attributes": { "class": "tmh_title" }, "elements":  [], "innerHTML": "lexicon.minh_menh", "selfClosing": false },
          { "name": "div", "attributes": { "class": "tmh_elements" }, "elements":  [
            { "name": "div", "attributes": { "class": "tmh_element_title" }, "elements":  [], "innerHTML": "lexicon.vdddtmdd", "selfClosing": false },
            { "name": "div", "attributes": { "class": "tmh_inscriptions" }, "elements":  [
              { "name": "span", "attributes": {}, "elements":  [], "innerHTML": "lexicon.obverse", "selfClosing": false },
              { "name": "span", "attributes": { "class": "tmh_inscription" }, "elements":  [], "innerHTML": "inscriptions.c5u3bjqm", "selfClosing": false },
              { "name": "span", "attributes": {}, "elements":  [], "innerHTML": "lexicon.reverse", "selfClosing": false },
              { "name": "span", "attributes": { "class": "tmh_inscription" }, "elements":  [], "innerHTML": "inscriptions.dfysid7w", "selfClosing": false }
            ], "innerHTML": "", "selfClosing": false },
            { "name": "div", "attributes": { "class": "tmh_specimen" }, "elements":  [
              { "name": "span", "attributes": { "class": "tmh_specimen_info", "name": "24" }, "elements":  [], "innerHTML": "lexicon.BTTPHCM_MM", "selfClosing": false }
            ], "innerHTML": "", "selfClosing": false },
            { "name": "div", "attributes": { "class": "tmh_image_route" }, "elements":  [
              { "name": "a", "attributes": { "class": "tmh_a_img", "href": "routes.3k292y7x", "title": "lexicon.mm_vdddtmdd" }, "elements":  [
                { "name": "img", "attributes": { "alt": "lexicon.mm_vdddtmdd", "class": "tmh_img", "src": "__IMAGES____PREVIEW_SIZE__/dad28005161846cd89d8e20673c38451-1.png" }, "elements":  [], "innerHTML": "", "selfClosing": true }
              ], "innerHTML": "", "selfClosing": false },
              { "name": "a", "attributes": { "class": "tmh_a_img", "href": "routes.3k292y7x", "title": "lexicon.mm_vdddtmdd" }, "elements":  [
                { "name": "img", "attributes": { "alt": "lexicon.mm_vdddtmdd", "class": "tmh_img", "src": "__IMAGES____PREVIEW_SIZE__/dad28005161846cd89d8e20673c38451-2.png" }, "elements":  [], "innerHTML": "", "selfClosing": true }
              ], "innerHTML": "", "selfClosing": false }
            ], "innerHTML": "", "selfClosing": false },
            { "name": "br", "attributes": {}, "elements":  [], "innerHTML": "", "selfClosing": true },
            { "name": "div", "attributes": { "class": "tmh_specimen" }, "elements":  [
              { "name": "span", "attributes": { "class": "tmh_specimen_info", "name": "1554" }, "elements":  [], "innerHTML": "lexicon.CMV_acronym", "selfClosing": false }
            ], "innerHTML": "", "selfClosing": false },
            { "name": "div", "attributes": { "class": "tmh_image_route" }, "elements":  [
              { "name": "a", "attributes": { "class": "tmh_a_img", "href": "routes.eb74yyyg", "title": "lexicon.mm_vdddtmdd" }, "elements":  [
                { "name": "img", "attributes": { "alt": "lexicon.mm_vdddtmdd", "class": "tmh_img", "src": "__IMAGES____PREVIEW_SIZE__/1d5597dd7e3342e3ae9e937def09048a-1.png" }, "elements":  [], "innerHTML": "", "selfClosing": true }
              ], "innerHTML": "", "selfClosing": false },
              { "name": "a", "attributes": { "class": "tmh_a_img", "href": "routes.eb74yyyg", "title": "lexicon.mm_vdddtmdd" }, "elements":  [
                { "name": "img", "attributes": { "alt": "lexicon.mm_vdddtmdd", "class": "tmh_img", "src": "__IMAGES____PREVIEW_SIZE__/1d5597dd7e3342e3ae9e937def09048a-2.png" }, "elements":  [], "innerHTML": "", "selfClosing": true }
              ], "innerHTML": "", "selfClosing": false }
            ], "innerHTML": "", "selfClosing": false },
            { "name": "br", "attributes": {}, "elements":  [], "innerHTML": "", "selfClosing": true },
            { "name": "div", "attributes": { "class": "tmh_specimen" }, "elements":  [
              { "name": "span", "attributes": { "class": "tmh_specimen_info", "name": "1983-0619-239" }, "elements":  [], "innerHTML": "lexicon.BRMU_acronym", "selfClosing": false }
            ], "innerHTML": "", "selfClosing": false },
            { "name": "div", "attributes": { "class": "tmh_image_route" }, "elements":  [
              { "name": "a", "attributes": { "class": "tmh_a_img", "href": "routes.8f5q88bo", "title": "lexicon.mm_vdddtmdd" }, "elements":  [
                { "name": "img", "attributes": { "alt": "lexicon.mm_vdddtmdd", "class": "tmh_img", "src": "__IMAGES____PREVIEW_SIZE__/aa9854d143044ec8b7dfc31815d860e5-1.png" }, "elements":  [], "innerHTML": "", "selfClosing": true }
              ], "innerHTML": "", "selfClosing": false },
              { "name": "a", "attributes": { "class": "tmh_a_img", "href": "routes.8f5q88bo", "title": "lexicon.mm_vdddtmdd" }, "elements":  [
                { "name": "img", "attributes": { "alt": "lexicon.mm_vdddtmdd", "class": "tmh_img", "src": "__IMAGES____PREVIEW_SIZE__/aa9854d143044ec8b7dfc31815d860e5-2.png" }, "elements":  [], "innerHTML": "", "selfClosing": true }
              ], "innerHTML": "", "selfClosing": false }
            ], "innerHTML": "", "selfClosing": false },
            { "name": "br", "attributes": {}, "elements":  [], "innerHTML": "", "selfClosing": true },
            { "name": "div", "attributes": { "class": "tmh_specimen" }, "elements":  [
              { "name": "a", "attributes": { "class": "tmh_a", "href": "routes.we98mux3", "title": "lexicon.mm_vdddtmdd", "name": "415" }, "elements":  [], "innerHTML": "lexicon.NA_acronym", "selfClosing": false }
            ], "innerHTML": "", "selfClosing": false },
            { "name": "div", "attributes": { "class": "tmh_specimen" }, "elements":  [
              { "name": "a", "attributes": { "class": "tmh_a", "href": "routes.hq5fxllk", "title": "lexicon.mm_vdddtmdd", "name": "145" }, "elements":  [], "innerHTML": "lexicon.AEN_acronym", "selfClosing": false }
            ], "innerHTML": "", "selfClosing": false },
            { "name": "div", "attributes": { "class": "tmh_specimen" }, "elements":  [
              { "name": "a", "attributes": { "class": "tmh_a", "href": "routes.b27weddq", "title": "lexicon.mm_vdddtmdd", "name": "40" }, "elements":  [], "innerHTML": "lexicon.AMD_MM", "selfClosing": false }
            ], "innerHTML": "", "selfClosing": false },
            { "name": "div", "attributes": { "class": "tmh_specimen" }, "elements":  [
              { "name": "a", "attributes": { "class": "tmh_a", "href": "routes.kvdnmrpk", "title": "lexicon.mm_vdddtmdd", "name": "V76" }, "elements":  [], "innerHTML": "lexicon.MDEO2_acronym", "selfClosing": false }
            ], "innerHTML": "", "selfClosing": false },
            { "name": "div", "attributes": { "class": "tmh_specimen" }, "elements":  [
              { "name": "a", "attributes": { "class": "tmh_a", "href": "routes.29a2uo4b", "title": "lexicon.mm_vdddtmdd", "name": "V77" }, "elements":  [], "innerHTML": "lexicon.MDEO2_acronym", "selfClosing": false }
            ], "innerHTML": "", "selfClosing": false },
            { "name": "div", "attributes": { "class": "tmh_specimen" }, "elements":  [
              { "name": "a", "attributes": { "class": "tmh_a", "href": "routes.kfqpxio4", "title": "lexicon.mm_vdddtmdd", "name": "V78" }, "elements":  [], "innerHTML": "lexicon.MDEO2_acronym", "selfClosing": false }
            ], "innerHTML": "", "selfClosing": false },
            { "name": "div", "attributes": { "class": "tmh_specimen" }, "elements":  [
              { "name": "a", "attributes": { "class": "tmh_a", "href": "routes.gqvyu9mj", "title": "lexicon.mm_vdddtmdd", "name": "18" }, "elements":  [], "innerHTML": "lexicon.PKMM_acronym", "selfClosing": false }
            ], "innerHTML": "", "selfClosing": false },
            { "name": "div", "attributes": { "class": "tmh_specimen" }, "elements":  [
              { "name": "a", "attributes": { "class": "tmh_a", "href": "routes.e0a3nh2o", "title": "lexicon.mm_vdddtmdd", "name": "43.1" }, "elements":  [], "innerHTML": "lexicon.ANZDQ", "selfClosing": false }
            ], "innerHTML": "", "selfClosing": false },
            { "name": "div", "attributes": { "class": "tmh_specimen" }, "elements":  [
              { "name": "a", "attributes": { "class": "tmh_a", "href": "routes.cbn51s2p", "title": "lexicon.mm_vdddtmdd", "name": "832" }, "elements":  [], "innerHTML": "lexicon.MADP_acronym", "selfClosing": false }
            ], "innerHTML": "", "selfClosing": false },
            { "name": "div", "attributes": { "class": "tmh_specimen" }, "elements":  [
              { "name": "a", "attributes": { "class": "tmh_a", "href": "routes.feicgh8t", "title": "lexicon.mm_vdddtmdd", "name": "3" }, "elements":  [], "innerHTML": "lexicon.ANMHDQTP", "selfClosing": false }
            ], "innerHTML": "", "selfClosing": false },
            { "name": "div", "attributes": { "class": "tmh_specimen" }, "elements":  [
              { "name": "a", "attributes": { "class": "tmh_a", "href": "routes.i4e5r8ul", "title": "lexicon.mm_vdddtmdd", "name": "13" }, "elements":  [], "innerHTML": "lexicon.IKARU_MM", "selfClosing": false }
            ], "innerHTML": "", "selfClosing": false },
            { "name": "div", "attributes": { "class": "tmh_specimen" }, "elements":  [
              { "name": "a", "attributes": { "class": "tmh_a", "href": "routes.m7ssjkqm", "title": "lexicon.mm_vdddtmdd", "name": "18.1" }, "elements":  [], "innerHTML": "lexicon.ILOT_MM", "selfClosing": false }
            ], "innerHTML": "", "selfClosing": false },
            { "name": "br", "attributes": {}, "elements":  [], "innerHTML": "", "selfClosing": true },
            { "name": "div", "attributes": { "class": "tmh_element_title" }, "elements":  [], "innerHTML": "lexicon.references", "selfClosing": false },
            { "name": "div", "attributes": { "class": "tmh_references" }, "elements":  [
              { "name": "div", "attributes": { "class": "tmh_reference" }, "elements":  [
                { "name": "span", "attributes": {}, "elements":  [], "innerHTML": "lexicon.BTTPHCM_MM_full", "selfClosing": false }
              ], "innerHTML": "", "selfClosing": false },
              { "name": "div", "attributes": { "class": "tmh_reference" }, "elements":  [
                { "name": "span", "attributes": {}, "elements":  [], "innerHTML": "lexicon.BTLSQG_full", "selfClosing": false }
              ], "innerHTML": "", "selfClosing": false },
              { "name": "div", "attributes": { "class": "tmh_reference" }, "elements":  [
                { "name": "span", "attributes": {}, "elements":  [], "innerHTML": "lexicon.BRMU_full", "selfClosing": false }
              ], "innerHTML": "", "selfClosing": false },
              { "name": "div", "attributes": { "class": "tmh_reference" }, "elements":  [
                { "name": "span", "attributes": {}, "elements":  [], "innerHTML": "lexicon.ANMHDQYJ_full", "selfClosing": false },
                { "name": "span", "attributes": { "name": "69,129,217" }, "elements":  [], "innerHTML": "lexicon.page", "selfClosing": false }
              ], "innerHTML": "", "selfClosing": false },
              { "name": "div", "attributes": { "class": "tmh_reference" }, "elements":  [
                { "name": "span", "attributes": {}, "elements":  [], "innerHTML": "lexicon.VN4_full", "selfClosing": false },
                { "name": "span", "attributes": { "name": "11" }, "elements":  [], "innerHTML": "lexicon.page", "selfClosing": false }
              ], "innerHTML": "", "selfClosing": false },
              { "name": "div", "attributes": { "class": "tmh_reference" }, "elements":  [
                { "name": "span", "attributes": {}, "elements":  [], "innerHTML": "lexicon.STTMM_full", "selfClosing": false },
                { "name": "span", "attributes": { "name": "92" }, "elements":  [], "innerHTML": "lexicon.page", "selfClosing": false }
              ], "innerHTML": "", "selfClosing": false },
              { "name": "div", "attributes": { "class": "tmh_reference" }, "elements":  [
                { "name": "span", "attributes": {}, "elements":  [], "innerHTML": "lexicon.ANMHDQTP_full", "selfClosing": false },
                { "name": "span", "attributes": { "name": "3" }, "elements":  [], "innerHTML": "lexicon.page", "selfClosing": false }
              ], "innerHTML": "", "selfClosing": false },
              { "name": "div", "attributes": { "class": "tmh_reference" }, "elements":  [
                { "name": "span", "attributes": {}, "elements":  [], "innerHTML": "lexicon.MADP_full", "selfClosing": false },
                { "name": "span", "attributes": { "name": "149" }, "elements":  [], "innerHTML": "lexicon.page", "selfClosing": false }
              ], "innerHTML": "", "selfClosing": false },
              { "name": "div", "attributes": { "class": "tmh_reference" }, "elements":  [
                { "name": "span", "attributes": {}, "elements":  [], "innerHTML": "lexicon.CMVC_full", "selfClosing": false },
                { "name": "span", "attributes": { "name": "393" }, "elements":  [], "innerHTML": "lexicon.page", "selfClosing": false }
              ], "innerHTML": "", "selfClosing": false },
              { "name": "div", "attributes": { "class": "tmh_reference" }, "elements":  [
                { "name": "span", "attributes": {}, "elements":  [], "innerHTML": "lexicon.ANZDQ_full", "selfClosing": false },
                { "name": "span", "attributes": { "name": "43" }, "elements":  [], "innerHTML": "lexicon.page", "selfClosing": false }
              ], "innerHTML": "", "selfClosing": false },
              { "name": "div", "attributes": { "class": "tmh_reference" }, "elements":  [
                { "name": "span", "attributes": {}, "elements":  [], "innerHTML": "lexicon.TCVN2_full", "selfClosing": false },
                { "name": "span", "attributes": { "name": "119" }, "elements":  [], "innerHTML": "lexicon.page", "selfClosing": false }
              ], "innerHTML": "", "selfClosing": false },
              { "name": "div", "attributes": { "class": "tmh_reference" }, "elements":  [
                { "name": "span", "attributes": {}, "elements":  [], "innerHTML": "lexicon.DNTL3_full", "selfClosing": false },
                { "name": "span", "attributes": { "name": "70" }, "elements":  [], "innerHTML": "lexicon.page", "selfClosing": false }
              ], "innerHTML": "", "selfClosing": false },
              { "name": "div", "attributes": { "class": "tmh_reference" }, "elements":  [
                { "name": "span", "attributes": {}, "elements":  [], "innerHTML": "lexicon.TCVN_full", "selfClosing": false },
                { "name": "span", "attributes": { "name": "170" }, "elements":  [], "innerHTML": "lexicon.page", "selfClosing": false }
              ], "innerHTML": "", "selfClosing": false },
              { "name": "div", "attributes": { "class": "tmh_reference" }, "elements":  [
                { "name": "span", "attributes": {}, "elements":  [], "innerHTML": "lexicon.PKMM_full", "selfClosing": false },
                { "name": "span", "attributes": { "name": "64" }, "elements":  [], "innerHTML": "lexicon.page", "selfClosing": false }
              ], "innerHTML": "", "selfClosing": false },
              { "name": "div", "attributes": { "class": "tmh_reference" }, "elements":  [
                { "name": "span", "attributes": {}, "elements":  [], "innerHTML": "lexicon.CMV_full", "selfClosing": false },
                { "name": "span", "attributes": { "name": "88," }, "elements":  [], "innerHTML": "lexicon.page", "selfClosing": false },
                { "name": "span", "attributes": { "name": "24" }, "elements":  [], "innerHTML": "lexicon.plate", "selfClosing": false }
              ], "innerHTML": "", "selfClosing": false },
              { "name": "div", "attributes": { "class": "tmh_reference" }, "elements":  [
                { "name": "span", "attributes": {}, "elements":  [], "innerHTML": "lexicon.MDEO2_full", "selfClosing": false },
                { "name": "span", "attributes": { "name": "50," }, "elements":  [], "innerHTML": "lexicon.page", "selfClosing": false },
                { "name": "span", "attributes": { "name": "11" }, "elements":  [], "innerHTML": "lexicon.plate", "selfClosing": false }
              ], "innerHTML": "", "selfClosing": false },
              { "name": "div", "attributes": { "class": "tmh_reference" }, "elements":  [
                { "name": "span", "attributes": {}, "elements":  [], "innerHTML": "lexicon.TCMM_full", "selfClosing": false },
                { "name": "span", "attributes": { "name": "48" }, "elements":  [], "innerHTML": "lexicon.page", "selfClosing": false }
              ], "innerHTML": "", "selfClosing": false },
              { "name": "div", "attributes": { "class": "tmh_reference" }, "elements":  [
                { "name": "span", "attributes": {}, "elements":  [], "innerHTML": "lexicon.COTA_full", "selfClosing": false },
                { "name": "span", "attributes": { "name": "11,95" }, "elements":  [], "innerHTML": "lexicon.page", "selfClosing": false }
              ], "innerHTML": "", "selfClosing": false },
              { "name": "div", "attributes": { "class": "tmh_reference" }, "elements":  [
                { "name": "span", "attributes": {}, "elements":  [], "innerHTML": "lexicon.CAC_full", "selfClosing": false },
                { "name": "span", "attributes": { "name": "11," }, "elements":  [], "innerHTML": "lexicon.page", "selfClosing": false },
                { "name": "span", "attributes": { "name": "15" }, "elements":  [], "innerHTML": "lexicon.plate", "selfClosing": false }
              ], "innerHTML": "", "selfClosing": false },
              { "name": "div", "attributes": { "class": "tmh_reference" }, "elements":  [
                { "name": "span", "attributes": {}, "elements":  [], "innerHTML": "lexicon.AMD_full", "selfClosing": false },
                { "name": "span", "attributes": { "name": "830" }, "elements":  [], "innerHTML": "lexicon.page", "selfClosing": false }
              ], "innerHTML": "", "selfClosing": false },
              { "name": "div", "attributes": { "class": "tmh_reference" }, "elements":  [
                { "name": "span", "attributes": {}, "elements":  [], "innerHTML": "lexicon.APCH_16_full", "selfClosing": false },
                { "name": "span", "attributes": { "name": "58,61" }, "elements":  [], "innerHTML": "lexicon.page", "selfClosing": false }
              ], "innerHTML": "", "selfClosing": false },
              { "name": "div", "attributes": { "class": "tmh_reference" }, "elements":  [
                { "name": "span", "attributes": {}, "elements":  [], "innerHTML": "lexicon.AEN_full", "selfClosing": false },
                { "name": "span", "attributes": { "name": "432," }, "elements":  [], "innerHTML": "lexicon.page", "selfClosing": false },
                { "name": "span", "attributes": { "name": "60" }, "elements":  [], "innerHTML": "lexicon.plate", "selfClosing": false }
              ], "innerHTML": "", "selfClosing": false },
              { "name": "div", "attributes": { "class": "tmh_reference" }, "elements":  [
                { "name": "span", "attributes": {}, "elements":  [], "innerHTML": "lexicon.NA_full", "selfClosing": false },
                { "name": "span", "attributes": { "name": "179," }, "elements":  [], "innerHTML": "lexicon.page", "selfClosing": false },
                { "name": "span", "attributes": { "name": "29" }, "elements":  [], "innerHTML": "lexicon.plate", "selfClosing": false }
              ], "innerHTML": "", "selfClosing": false },
              { "name": "div", "attributes": { "class": "tmh_reference" }, "elements":  [
                { "name": "span", "attributes": {}, "elements":  [], "innerHTML": "lexicon.DNTLCB_MM_full", "selfClosing": false }
              ], "innerHTML": "", "selfClosing": false }
            ], "innerHTML": "", "selfClosing": false },
            { "name": "br", "attributes": {}, "elements":  [], "innerHTML": "", "selfClosing": true },
            { "name": "div", "attributes": { "class": "tmh_creative_commons" }, "elements":  [
              { "name": "span", "attributes": {}, "elements":  [], "innerHTML": "lexicon.cc_this_image", "selfClosing": false },
              { "name": "span", "attributes": {}, "elements":  [], "innerHTML": "lexicon.cc_licensed", "selfClosing": false },
              { "name": "br", "attributes": {}, "elements":  [], "innerHTML": "", "selfClosing": true },
              { "name": "div", "attributes": { "class": "tmh_image_route" }, "elements":  [
                { "name": "a", "attributes": { "class": "tmh_a_external", "href": "lexicon.cc_deed_url", "rel": "license", "target": "_blank", "title": "lexicon.cc_image_alt" }, "elements":  [], "innerHTML": "lexicon.cc_url_text", "selfClosing": false }
              ], "innerHTML": "", "selfClosing": false }
            ], "innerHTML": "", "selfClosing": false }
          ], "innerHTML": "", "selfClosing": false }
        ], "innerHTML": "", "selfClosing": false }
      ], "innerHTML": "", "selfClosing": false }
    ], "innerHTML": "", "selfClosing": false }
  ]
}