{
  "page_image": "2b8540de8c62475fa9de313ca46e7ec4-2",
  "images": [
    { "image_id": "1", "uuid": "cb3rqayi", "src": "957923a1ec9344ed87520613ea15caef-1.png", "href": "CFE_1317", "copyright": "1", "country": "hk", "year": "1895", "color": "0", "visible": "1" },
    { "image_id": "2", "uuid": "jz0rypih", "src": "957923a1ec9344ed87520613ea15caef-2.png", "href": "CFE_1317", "copyright": "1", "country": "hk", "year": "1895", "color": "0", "visible": "1" },
    { "image_id": "3", "uuid": "44atzio7", "src": "3dfafd46175345bfaa7113352d030696-2.png", "href": "NA_420", "copyright": "0", "country": "fr", "year": "1900", "color": "0", "visible": "1" },
    { "image_id": "4", "uuid": "e1rw8541", "src": "c9b9d01eb99a4278a72492a84bc8c090-1.png", "href": "AS3_08", "copyright": "1", "country": "ja", "year": "1971", "color": "0", "visible": "1" },
    { "image_id": "5", "uuid": "7j35k7dz", "src": "c9b9d01eb99a4278a72492a84bc8c090-2.png", "href": "AS3_08", "copyright": "1", "country": "ja", "year": "1971", "color": "0", "visible": "1" },
    { "image_id": "6", "uuid": "ffp0gvyo", "src": "0dd1f865f6344c889d91e92beb497df1-1.png", "href": "HCCV_156", "copyright": "1", "country": "sg", "year": "2004", "color": "0", "visible": "1" },
    { "image_id": "7", "uuid": "tnrap3x1", "src": "0dd1f865f6344c889d91e92beb497df1-2.png", "href": "HCCV_156", "copyright": "1", "country": "sg", "year": "2004", "color": "0", "visible": "1" },
    { "image_id": "8", "uuid": "l0bue2kw", "src": "c748d41655684d11b84a6e9040cdbcaa-1.png", "href": "HCCV_156", "copyright": "1", "country": "sg", "year": "2004", "color": "1", "visible": "0" },
    { "image_id": "9", "uuid": "fvysdzns", "src": "c748d41655684d11b84a6e9040cdbcaa-2.png", "href": "HCCV_156", "copyright": "1", "country": "sg", "year": "2004", "color": "1", "visible": "0" },
    { "image_id": "10", "uuid": "x37q7urf", "src": "f31604f4e6e948dfbe90347067a91594-1.png", "href": "ANZDQ_24", "copyright": "1", "country": "ja", "year": "2010", "color": "0", "visible": "1" },
    { "image_id": "11", "uuid": "w39kmlyz", "src": "f31604f4e6e948dfbe90347067a91594-2.png", "href": "ANZDQ_24", "copyright": "1", "country": "ja", "year": "2010", "color": "0", "visible": "1" },
    { "image_id": "12", "uuid": "d3m9q1sq", "src": "801f04cc0bb7426c8b387bbdaaf5ae80-1.png", "href": "MAJS_MM1", "copyright": "1", "country": "fr", "year": "2011", "color": "0", "visible": "1" },
    { "image_id": "13", "uuid": "0z4ghtk9", "src": "801f04cc0bb7426c8b387bbdaaf5ae80-2.png", "href": "MAJS_MM1", "copyright": "1", "country": "fr", "year": "2011", "color": "0", "visible": "1" },
    { "image_id": "14", "uuid": "pqdwu11p", "src": "4b7e1443452e4bc6b49150ee6a76120c-1.png", "href": "MAJS_MM1", "copyright": "1", "country": "fr", "year": "2011", "color": "1", "visible": "0" },
    { "image_id": "15", "uuid": "utnljozy", "src": "4b7e1443452e4bc6b49150ee6a76120c-2.png", "href": "MAJS_MM1", "copyright": "1", "country": "fr", "year": "2011", "color": "1", "visible": "0" },
    { "image_id": "16", "uuid": "udm3src6", "src": "abeb4158e0d84222ae8669b136ebbccc-1.png", "href": "AMDK_12", "copyright": "1", "country": "ja", "year": "2012", "color": "0", "visible": "1" },
    { "image_id": "17", "uuid": "3skp0536", "src": "abeb4158e0d84222ae8669b136ebbccc-2.png", "href": "AMDK_12", "copyright": "1", "country": "ja", "year": "2012", "color": "0", "visible": "1" },
    { "image_id": "18", "uuid": "ooswz31u", "src": "2b8540de8c62475fa9de313ca46e7ec4-1.png", "href": "STTMM_17", "copyright": "1", "country": "vn", "year": "2013", "color": "0", "visible": "1" },
    { "image_id": "19", "uuid": "jcgw4c0y", "src": "2b8540de8c62475fa9de313ca46e7ec4-2.png", "href": "STTMM_17", "copyright": "1", "country": "vn", "year": "2013", "color": "0", "visible": "1" },
    { "image_id": "20", "uuid": "4ltdmt2t", "src": "d9c3c0993dec4c3dac547b9ce19f56c9-1.png", "href": "STTMM_17", "copyright": "1", "country": "vn", "year": "2013", "color": "1", "visible": "1" },
    { "image_id": "21", "uuid": "ptl0spxk", "src": "d9c3c0993dec4c3dac547b9ce19f56c9-2.png", "href": "STTMM_17", "copyright": "1", "country": "vn", "year": "2013", "color": "1" , "visible": "1"},
    { "image_id": "22", "uuid": "ixnl3ngi", "src": "b3d2fd7f7b4b48a8a82d65bdf5e41d18-1.png", "href": "HCCV_156", "copyright": "0", "country": "cn", "year": "2017", "color": "0", "visible": "1" },
    { "image_id": "23", "uuid": "lqn6b1w2", "src": "b3d2fd7f7b4b48a8a82d65bdf5e41d18-2.png", "href": "HCCV_156", "copyright": "0", "country": "cn", "year": "2017", "color": "0", "visible": "1" },
    { "image_id": "24", "uuid": "3896ydsk", "src": "265c63da809c4425b73303b161f2af36-1.png", "href": "HCCV_156", "copyright": "0", "country": "cn", "year": "2017", "color": "1", "visible": "0" },
    { "image_id": "25", "uuid": "ems6506e", "src": "265c63da809c4425b73303b161f2af36-2.png", "href": "HCCV_156", "copyright": "0", "country": "cn", "year": "2017", "color": "1", "visible": "0" },
    { "image_id": "26", "uuid": "qtw314z3", "src": "03ac8e9cae8e45f495d22133ec6248d0-1.png", "href": "VN4_VN29_3", "copyright": "1", "country": "vn", "year": "2018", "color": "0", "visible": "1" },
    { "image_id": "27", "uuid": "um4q1151", "src": "03ac8e9cae8e45f495d22133ec6248d0-2.png", "href": "VN4_VN29_3", "copyright": "1", "country": "vn", "year": "2018", "color": "0", "visible": "1" },
    { "image_id": "28", "uuid": "e1pbxwie", "src": "9b027906aa074572921c7cbdb0a02119-1.png", "href": "VN4_VN29_3", "copyright": "1", "country": "vn", "year": "2018", "color": "1", "visible": "0" },
    { "image_id": "29", "uuid": "0n1a3h9t", "src": "9b027906aa074572921c7cbdb0a02119-2.png", "href": "VN4_VN29_3", "copyright": "1", "country": "vn", "year": "2018", "color": "1", "visible": "0" }
  ],
  "reference_specimens": [
    { "code": "Lockhart 1317", "images": ["cb3rqayi", "jz0rypih"], "variant": "", "diameter": "", "weight": "", "page": "115", "plate": "130", "articles": [], "urls": [] },
    { "code": "Lacroix 420", "images": ["44atzio7"], "variant": "", "diameter": "", "weight": "", "page": "180", "plate": "29", "articles": [], "urls": [] },
    { "code": "三浦清吾 8", "images": ["e1rw8541", "7j35k7dz"], "variant": "", "diameter": "", "weight": "", "page": "12", "plate": "", "articles": [], "urls": [] },
    { "code": "Barker 156", "images": ["ixnl3ngi", "lqn6b1w2"], "variant": "", "diameter": "50.97", "weight": "29.98", "page": "281", "plate": "", "articles": [], "urls": [] },
    { "code": "大庫隆夫 24", "images": ["x37q7urf", "w39kmlyz"], "variant": "", "diameter": "", "weight": "", "page": "52", "plate": "", "articles": [], "urls": [] },
    { "code": "Joyaux MM1", "images": ["d3m9q1sq", "0z4ghtk9"], "variant": "", "diameter": "", "weight": "", "page": "22", "plate": "", "articles": [], "urls": [] },
    { "code": "満泉堂 12", "images": ["udm3src6", "3skp0536"], "variant": "", "diameter": "", "weight": "", "page": "12", "plate": "", "articles": [], "urls": [] },
    { "code": "STTMM 17", "images": ["ooswz31u", "jcgw4c0y"], "variant": "", "diameter": "51.00", "weight": "26.20", "page": "91", "plate": "", "articles": [], "urls": [] },
    { "code": "VN29-3", "images": ["qtw314z3", "um4q1151"], "variant": "", "diameter": "", "weight": "", "page": "11", "plate": "", "articles": [], "urls": [] }
  ],
  "references": [
    { "reference_uuid": "59out4lc", "page": "35", "plate": "", "identifier": "", "notes": "", "articles": [], "urls": [] },
    { "reference_uuid": "og0l2xmu", "page": "132", "plate": "", "identifier": "", "notes": "", "articles": [], "urls": [] },
    { "reference_uuid": "1e7z5uyq", "page": "106", "plate": "", "identifier": "", "notes": "", "articles": [], "urls": [] },
    { "reference_uuid": "aedgta41", "page": "115", "plate": "130", "identifier": "1317", "notes": "", "articles": [], "urls": [] },
    { "reference_uuid": "egjosprx", "page": "180", "plate": "29", "identifier": "420", "notes": "", "articles": [], "urls": [] },
    { "reference_uuid": "nlyz7za5", "page": "12", "plate": "", "identifier": "", "notes": "", "articles": [], "urls": [] },
    { "reference_uuid": "8eszq2lc", "page": "48", "plate": "", "identifier": "22", "notes": "", "articles": [], "urls": [] },
    { "reference_uuid": "rybfmx61", "page": "64", "plate": "", "identifier": "17", "notes": "", "articles": [], "urls": [] },
    { "reference_uuid": "57qxr0k8", "page": "169", "plate": "", "identifier": "178", "notes": "", "articles": [], "urls": [] },
    { "reference_uuid": "5ekjpp24", "page": "281", "plate": "", "identifier": "156", "notes": "", "articles": [], "urls": [] },
    { "reference_uuid": "drq2opmz", "page": "70", "plate": "", "identifier": "", "notes": "", "articles": [], "urls": [] },
    { "reference_uuid": "vt6sjmp6", "page": "119", "plate": "", "identifier": "", "notes": "", "articles": [], "urls": [] },
    { "reference_uuid": "pe4aw1hq", "page": "52", "plate": "", "identifier": "24", "notes": "", "articles": [], "urls": [] },
    { "reference_uuid": "ybfi7983", "page": "393", "plate": "", "identifier": "41", "notes": "", "articles": []},
    { "reference_uuid": "aslzlpzl", "page": "22", "plate": "", "identifier": "", "notes": "", "articles": [], "urls": [] },
    { "reference_uuid": "cxqs7bca", "page": "12", "plate": "", "identifier": "12", "notes": "", "articles": [], "urls": [] },
    { "reference_uuid": "u3yk53j3", "page": "91", "plate": "", "identifier": "17", "notes": "", "articles": [], "urls": [] },
    { "reference_uuid": "0qynj8k8", "page": "11", "plate": "", "identifier": "VN29-3", "notes": "btlsqg", "articles": [], "urls": [] },
    { "reference_uuid": "jybo2v6v", "page": "216", "plate": "", "identifier": "41", "notes": "cmv_partial_copy", "articles": [], "urls": [] },
    { "reference_uuid": "08w1apoy", "page": "", "plate": "", "identifier": "1983,0619.247", "notes": "", "articles": [], "urls": [] }
  ],
  "other_specimens": [
    { "code": "KYQS MM2", "images": ["0dfvm04g", "yfrf4n7r"], "variant": "", "diameter": "", "weight": "", "page": "", "plate": "" },
    { "code": "HUAY MM7", "images": ["laxy713c", "5tvtt49x"], "variant": "", "diameter": "", "weight": "", "page": "", "plate": "" },
    { "code": "LAVA MM2", "images": ["ricamqvw", "n9vdynnt"], "variant": "", "diameter": "50.80", "weight": "27.50", "page": "", "plate": "" }
  ],
  "other_images": [
    { "image_id": "30", "uuid": "0dfvm04g", "src": "9a59803e4e614223827a35d5d3cf6bf9-1.png", "href": "KYQS MM2", "copyright": "0", "country": "cn", "year": "2010", "color": "0", "visible": "1" },
    { "image_id": "31", "uuid": "yfrf4n7r", "src": "9a59803e4e614223827a35d5d3cf6bf9-2.png", "href": "KYQS MM2", "copyright": "0", "country": "cn", "year": "2010", "color": "0", "visible": "1" },
    { "image_id": "32", "uuid": "vdzmkune", "src": "f137ea6d53a240009dc2c3954630f77a-1.png", "href": "KYQS MM2", "copyright": "0", "country": "cn", "year": "2010", "color": "1", "visible": "0" },
    { "image_id": "33", "uuid": "hjj89uvy", "src": "f137ea6d53a240009dc2c3954630f77a-2.png", "href": "KYQS MM2", "copyright": "0", "country": "cn", "year": "2010", "color": "1", "visible": "0" },
    { "image_id": "34", "uuid": "laxy713c", "src": "dfab9d342f194502baeb71d694850e70-1.png", "href": "HUAY MM7", "copyright": "0", "country": "cn", "year": "2013", "color": "0", "visible": "1" },
    { "image_id": "35", "uuid": "5tvtt49x", "src": "dfab9d342f194502baeb71d694850e70-2.png", "href": "HUAY MM7", "copyright": "0", "country": "cn", "year": "2013", "color": "0", "visible": "1" },
    { "image_id": "36", "uuid": "spchol1q", "src": "a161401b0f454087bbe38b7fcc21b8f6-1.png", "href": "HUAY MM7", "copyright": "0", "country": "cn", "year": "2013", "color": "1", "visible": "0" },
    { "image_id": "37", "uuid": "8jqg0msw", "src": "a161401b0f454087bbe38b7fcc21b8f6-2.png", "href": "HUAY MM7", "copyright": "0", "country": "cn", "year": "2013", "color": "1", "visible": "0" },
    { "image_id": "38", "uuid": "ricamqvw", "src": "f0730c1ccda74f02a351fac9d8b32f64-1.png", "href": "LAVA MM2", "copyright": "0", "country": "fr", "year": "2019", "color": "0", "visible": "1" },
    { "image_id": "39", "uuid": "n9vdynnt", "src": "f0730c1ccda74f02a351fac9d8b32f64-2.png", "href": "LAVA MM2", "copyright": "0", "country": "fr", "year": "2019", "color": "0", "visible": "1" },
    { "image_id": "40", "uuid": "zip9vmg1", "src": "cf00789747dc40f2a43186ad58d51a09-1.png", "href": "LAVA MM2", "copyright": "0", "country": "fr", "year": "2019", "color": "1", "visible": "0" },
    { "image_id": "41", "uuid": "g82glcfu", "src": "cf00789747dc40f2a43186ad58d51a09-2.png", "href": "LAVA MM2", "copyright": "0", "country": "fr", "year": "2019", "color": "1", "visible": "0" }
  ],
  "collections": [
    { "collection_uuid": "fvfxlmvl", "date": "2010-03-21", "pdf_url": "", "url_obverse": "http://img1.tienmyhieu.com/uploads/1003311821412fec58bb6ed823.jpg", "url_reverse": "http://img1.tienmyhieu.com/uploads/1003311821c655d6d9ac7a2e74.jpg", "identifier": "", "lot_number": "" },
    { "collection_uuid": "0i5gqe5p", "date": "2013-05-30", "pdf_url": "", "url_obverse": "http://imgali.hxgqw.com/pic/2013/0530/2013053013424989735798.jpg", "url_reverse": "http://imgali.hxgqw.com/pic/2013/0530/2013053013424721364057.jpg", "identifier": "", "lot_number": "" },
    { "collection_uuid": "o2cf2ev8", "date": "2019-06-21", "pdf_url": "", "url_obverse": "https://www.zeno.ru/data/11015/Minh_Mang_my_hi_u_wxz1470_50_8mm_27_50g.jpg", "url_reverse": "https://www.zeno.ru/data/11015/Minh_Mang_my_hi_u_wxz1470_50_8mm_27_50g.jpg", "identifier": "", "lot_number": "" }
  ]
}